README.md
aiourpc.py
setup.cfg
setup.py
urpc.py
scripts/urpc-cli
urpc.egg-info/PKG-INFO
urpc.egg-info/SOURCES.txt
urpc.egg-info/dependency_links.txt
urpc.egg-info/requires.txt
urpc.egg-info/top_level.txt