Metadata-Version: 1.1
Name: urpc
Version: 0.2.0
Summary: uRPC is oversimplistic RPC over Redis
Home-page: http://github.com/bobuk/urpc
Author: Grigory Bakunov
Author-email: thebobuk@ya.ru
License: UNKNOWN
Platform: UNKNOWN
Classifier: Programming Language :: Python
Classifier: Programming Language :: Python :: 3
Classifier: Development Status :: 4 - Beta
Classifier: Environment :: Other Environment
Classifier: Intended Audience :: Developers
Classifier: Operating System :: OS Independent
Classifier: Topic :: Software Development :: Libraries :: Python Modules
